setup.cfg
setup.py
easy_shortcut/__init__.py
easy_shortcut.egg-info/PKG-INFO
easy_shortcut.egg-info/SOURCES.txt
easy_shortcut.egg-info/dependency_links.txt
easy_shortcut.egg-info/not-zip-safe
easy_shortcut.egg-info/requires.txt
easy_shortcut.egg-info/top_level.txt