Metadata-Version: 1.0
Name: easy-shortcut
Version: 0.0
Summary: Easy make shortcut
Home-page: UNKNOWN
Author: UNKNOWN
Author-email: foton-pc@inbox.ru
License: UNKNOWN
Platform: UNKNOWN
